titanicsp/__init__.py
titanicsp/abstractest.py
titanicsp/prediction.py
titanicsp/utils.py
titanicsp-0.0.1.dist-info/METADATA
titanicsp-0.0.1.dist-info/WHEEL
titanicsp-0.0.1.dist-info/top_level.txt
titanicsp-0.0.1.dist-info/RECORD
