Metadata-Version: 2.1
Name: titanicsp
Version: 0.0.1
Summary: Titanic Survived Prediction
Home-page: https://github.com/abbiyanaila/titanicsp
Author: Desi Ratna Ningsih
Author-email: abbiyanaila@gmail.com
License: MIT
Platform: UNKNOWN
